LICENSE
MANIFEST.in
setup.py
nexus_redis/__init__.py
nexus_redis/conf.py
nexus_redis/helpers.py
nexus_redis/models.py
nexus_redis/nexus_modules.py
nexus_redis.egg-info/PKG-INFO
nexus_redis.egg-info/SOURCES.txt
nexus_redis.egg-info/dependency_links.txt
nexus_redis.egg-info/not-zip-safe
nexus_redis.egg-info/requires.txt
nexus_redis.egg-info/top_level.txt
nexus_redis/media/css/redis.css
nexus_redis/media/js/redis.js
nexus_redis/templates/nexus/redis/by_server.html
nexus_redis/templates/nexus/redis/dashboard.html
nexus_redis/templates/nexus/redis/index.html
nexus_redis/templatetags/__init__.py
nexus_redis/templatetags/redis_helpers.py