Metadata-Version: 1.0
Name: nexus-redis
Version: 0.3
Summary: Redis Plugin for Nexus
Home-page: http://github.com/dcramer/nexus-redis
Author: David Cramer
Author-email: dcramer@gmail.com
License: UNKNOWN
Platform: UNKNOWN
Classifier: Framework :: Django
Classifier: Intended Audience :: Developers
Classifier: Intended Audience :: System Administrators
Classifier: Operating System :: OS Independent
Classifier: Topic :: Software Development
